Workbook

Sheet Overview
B2: NMS TURNKEY DIGITAL GROWTH PROGRAMME
B3: Editable package selector and planning model | South Africa | ZAR | Generated 16 August 2026
B5: How to use this workbook
B6: Start in Package Builder: choose a package and 3, 6, 9 or 12-month commitment. Then select optional items in Add-Ons and enter commercial assumptions in ROI Model. Yellow cells are inputs; green cells are calculated. All returns are planning scenarios, not guarantees.
B10: Package comparison
B11: Package | C11: Monthly budget | D11: Service delivery | E11: Media allowance | F11: Tools allowance | G11: Best fit
B12: Foundation | C12: 20000 | D12: 14500 | E12: 3000 | F12: 2500 | G12: Credible launch foundation and lead capture
B13: Launch | C13: 35000 | D13: 24500 | E13: 7500 | F13: 3000 | G13: Brand, store and content engine go live
B14: Growth | C14: 50000 | D14: 32500 | E14: 14000 | F14: 3500 | G14: Always-on acquisition, SEO and automation
B15: Scale | C15: 75000 | D15: 45000 | E15: 25000 | F15: 5000 | G15: Multi-channel growth with higher content velocity
B16: Market Leader | C16: 100000 | D16: 57500 | E16: 35000 | F16: 7500 | G16: Full-funnel execution, experiments and senior oversight
B19: Commitment discounts
B20: Term | C20: Discount applied to service fee | D20: Commercial intent
B21: 3 months | C21: 0 | D21: Minimum validation and launch term
B22: 6 months | C22: 0.05 | D22: Build, learn and optimise
B23: 9 months | C23: 0.08 | D23: Mature channel and content systems
B24: 12 months | C24: 0.12 | D24: Best value; compound SEO, CRM and creative learning
B27: Workbook contents
B28: Package Builder | C28: Select package and term; view monthly and contract totals.
B29: Scope Matrix | C29: Compare the included service level across all packages.
B30: Add-Ons | C30: Switch optional monthly and once-off items on or off.
B31: ROI Model | C31: Test break-even orders, leads and revenue scenarios using your economics.
B34: Commercial note: package prices are exclusive of VAT. The displayed media and software amounts are planning allowances. Platforms and third-party providers are normally billed at cost and may change their tariffs. Commitment discounts apply only to the service-delivery component, never to media, software, production disbursements or external specialists.

Sheet Package Builder
B2: PACKAGE BUILDER
B3: Choose a monthly package and commitment term; totals update automatically
B5: Client selections
B6: Selected package | C6: Growth
B7: Commitment term (months) | C7: 6
B8: Include VAT in final cash requirement? | C8: Yes
B11: Calculated monthly budget
B12: List monthly budget | C12: =INDEX(Overview!$C$12:$C$16,MATCH($C$6,Overview!$B$12:$B$16,0)) -> 50000
B13: Service delivery before discount | C13: =INDEX(Overview!$D$12:$D$16,MATCH($C$6,Overview!$B$12:$B$16,0)) -> 32500
B14: Paid media allowance | C14: =INDEX(Overview!$E$12:$E$16,MATCH($C$6,Overview!$B$12:$B$16,0)) -> 14000
B15: Software/tools allowance | C15: =INDEX(Overview!$F$12:$F$16,MATCH($C$6,Overview!$B$12:$B$16,0)) -> 3500
B16: Commitment discount | C16: =IF(C7=3,0,IF(C7=6,5%,IF(C7=9,8%,12%))) -> 0.05
B17: Discounted service fee | C17: =C13*(1-C16) -> 30875
B18: Selected monthly add-ons | C18: ='Add-Ons'!G18 -> 0
B19: Revised recurring monthly total ex VAT | C19: =C17+C14+C15+C18 -> 48375
B22: Contract value and cash requirement
B23: Recurring contract value ex VAT | C23: =C19*C7 -> 290250
B24: Selected once-off add-ons ex VAT | C24: ='Add-Ons'!G19 -> 0
B25: Total contract value ex VAT | C25: =C23+C24 -> 290250
B26: VAT at 15% | C26: =C25*15% -> 43537.5
B27: Cash requirement based on VAT selection | C27: =IF(C8="Yes",C25+C26,C25) -> 333787.5
B28: Effective average per month | C28: =C27/C7 -> 55631.25
B31: 12-month cash-flow view
B32: Month | C32: Active? | D32: Recurring ex VAT | E32: Once-off ex VAT | F32: VAT | G32: Cash requirement
B33: 1 | C33: =IF(B33<=$C$7,"Yes","No") -> Yes | D33: =IF(C33="Yes",$C$19,0) -> 48375 | E33: =IF(B33=1,$C$24,0) -> 0 | F33: =IF($C$8="Yes",(D33+E33)*15%,0) -> 7256.25 | G33: =D33+E33+F33 -> 55631.25
B34: 2 | C34: =IF(B34<=$C$7,"Yes","No") -> Yes | D34: =IF(C34="Yes",$C$19,0) -> 48375 | E34: =IF(B34=1,$C$24,0) -> 0 | F34: =IF($C$8="Yes",(D34+E34)*15%,0) -> 7256.25 | G34: =D34+E34+F34 -> 55631.25
B35: 3 | C35: =IF(B35<=$C$7,"Yes","No") -> Yes | D35: =IF(C35="Yes",$C$19,0) -> 48375 | E35: =IF(B35=1,$C$24,0) -> 0 | F35: =IF($C$8="Yes",(D35+E35)*15%,0) -> 7256.25 | G35: =D35+E35+F35 -> 55631.25
B36: 4 | C36: =IF(B36<=$C$7,"Yes","No") -> Yes | D36: =IF(C36="Yes",$C$19,0) -> 48375 | E36: =IF(B36=1,$C$24,0) -> 0 | F36: =IF($C$8="Yes",(D36+E36)*15%,0) -> 7256.25 | G36: =D36+E36+F36 -> 55631.25
B37: 5 | C37: =IF(B37<=$C$7,"Yes","No") -> Yes | D37: =IF(C37="Yes",$C$19,0) -> 48375 | E37: =IF(B37=1,$C$24,0) -> 0 | F37: =IF($C$8="Yes",(D37+E37)*15%,0) -> 7256.25 | G37: =D37+E37+F37 -> 55631.25
B38: 6 | C38: =IF(B38<=$C$7,"Yes","No") -> Yes | D38: =IF(C38="Yes",$C$19,0) -> 48375 | E38: =IF(B38=1,$C$24,0) -> 0 | F38: =IF($C$8="Yes",(D38+E38)*15%,0) -> 7256.25 | G38: =D38+E38+F38 -> 55631.25
B39: 7 | C39: =IF(B39<=$C$7,"Yes","No") -> No | D39: =IF(C39="Yes",$C$19,0) -> 0 | E39: =IF(B39=1,$C$24,0) -> 0 | F39: =IF($C$8="Yes",(D39+E39)*15%,0) -> 0 | G39: =D39+E39+F39 -> 0
B40: 8 | C40: =IF(B40<=$C$7,"Yes","No") -> No | D40: =IF(C40="Yes",$C$19,0) -> 0 | E40: =IF(B40=1,$C$24,0) -> 0 | F40: =IF($C$8="Yes",(D40+E40)*15%,0) -> 0 | G40: =D40+E40+F40 -> 0
B41: 9 | C41: =IF(B41<=$C$7,"Yes","No") -> No | D41: =IF(C41="Yes",$C$19,0) -> 0 | E41: =IF(B41=1,$C$24,0) -> 0 | F41: =IF($C$8="Yes",(D41+E41)*15%,0) -> 0 | G41: =D41+E41+F41 -> 0
B42: 10 | C42: =IF(B42<=$C$7,"Yes","No") -> No | D42: =IF(C42="Yes",$C$19,0) -> 0 | E42: =IF(B42=1,$C$24,0) -> 0 | F42: =IF($C$8="Yes",(D42+E42)*15%,0) -> 0 | G42: =D42+E42+F42 -> 0
B43: 11 | C43: =IF(B43<=$C$7,"Yes","No") -> No | D43: =IF(C43="Yes",$C$19,0) -> 0 | E43: =IF(B43=1,$C$24,0) -> 0 | F43: =IF($C$8="Yes",(D43+E43)*15%,0) -> 0 | G43: =D43+E43+F43 -> 0
B44: 12 | C44: =IF(B44<=$C$7,"Yes","No") -> No | D44: =IF(C44="Yes",$C$19,0) -> 0 | E44: =IF(B44=1,$C$24,0) -> 0 | F44: =IF($C$8="Yes",(D44+E44)*15%,0) -> 0 | G44: =D44+E44+F44 -> 0

Sheet Scope Matrix
B2: SCOPE MATRIX
B3: Indicative inclusions; final statement of work follows discovery and compliance review
B5: Workstream | C5: Foundation | D5: Launch | E5: Growth | F5: Scale | G5: Market Leader
B6: Strategy & project leadership | C6: Monthly plan + one review | D6: Fortnightly sprint | E6: Weekly growth sprint | F6: Weekly cross-channel sprint | G6: Senior growth office + quarterly planning
B7: Brand identity & logo | C7: Logo refinement + mini guide | D7: New/refined identity + guide | E7: Identity system + templates | F7: Full brand toolkit + campaign system | G7: Full identity governance + rollout
B8: Copywriting | C8: Core website copy | D8: Website + product/service copy | E8: Conversion copy + 2 articles/mo | F8: Conversion copy + 4 articles/mo | G8: Editorial programme + thought leadership
B9: Website & online store | C9: Responsive site + starter store, up to 10 SKUs | D9: Store up to 25 SKUs + payment/shipping setup | E9: Store up to 50 SKUs + CRO landing pages | F9: Advanced store, bundles and subscriptions | G9: Custom commerce roadmap and ongoing CRO
B10: SEO | C10: Technical basics + local setup | D10: On-page SEO + keyword map | E10: Technical + content SEO monthly | F10: SEO content clusters + digital PR support | G10: Advanced SEO programme and authority building
B11: Social channels | C11: 2 priority channels | D11: 3 priority channels | E11: 4 channels | F11: 5 channels | G11: All relevant channels with repurposing
B12: Content cadence | C12: 8 static/short-form items per month | D12: 12 items + 2 short videos/mo | E12: 16 items + 4 short videos/mo | F12: 24 items + 8 short videos/mo | G12: 30+ items + 12 short videos/mo
B13: Paid media | C13: One platform; R3,000 media allowance | D13: Meta/search mix; R7,500 allowance | E13: Multi-campaign; R14,000 allowance | F13: Multi-channel; R25,000 allowance | G13: Full-funnel tests; R35,000 allowance
B14: Chatbot & lead capture | C14: FAQ bot + forms | D14: AI FAQ + lead qualification | E14: AI bot + human handoff + CRM | F14: Multi-channel bot + workflows | G14: Advanced knowledge base, QA and optimisation
B15: CRM, email & WhatsApp | C15: Lead inbox and basic email | D15: CRM pipeline + welcome flow | E15: Segmentation + nurture automation | F15: Lifecycle automation + WhatsApp workflows | G15: Advanced CRM operations and attribution
B16: Analytics & reporting | C16: Monthly scorecard | D16: Dashboard + monthly review | E16: Dashboard + funnel analysis | F16: Weekly optimisation + monthly board report | G16: Executive dashboard + experiments register
B17: Maintenance & support | C17: Hosting oversight, backups, security, 2 hrs changes | D17: 4 hrs changes + priority support | E17: 8 hrs changes + performance monitoring | F17: 12 hrs changes + priority SLA | G17: 20 hrs changes + senior technical oversight
B20: All packages assume timely client access, approved product information, compliant claims, feedback within two business days, and one nominated decision-maker. Major custom development, high-volume product migration, legal opinions, creator fees, stock, courier charges and payment-gateway transaction fees are excluded unless expressly added.

Sheet Add-Ons
B2: OPTIONAL ADD-ONS
B3: Select Yes in column F. Totals feed directly into Package Builder
B5: Add-on | C5: Billing | D5: Price ex VAT | E5: Scope note | F5: Selected? | G5: Selected value
B6: Additional paid media budget | C6: Monthly | D6: 5000 | E6: Media spend only; management fee may change at higher spend | F6: No | G6: =IF(F6="Yes",D6,0) -> 0
B7: Additional content pack: 4 posts | C7: Monthly | D7: 4500 | E7: Design, caption and scheduling | F7: No | G7: =IF(F7="Yes",D7,0) -> 0
B8: Additional short-form video pack: 4 | C8: Monthly | D8: 8500 | E8: Editing from supplied or planned footage; shoot costs separate | F8: No | G8: =IF(F8="Yes",D8,0) -> 0
B9: Professional photo/video shoot day | C9: Once-off | D9: 18000 | E9: Crew and editing allowance; travel/location costs separate | F9: No | G9: =IF(F9="Yes",D9,0) -> 0
B10: Influencer activation management | C10: Monthly | D10: 7500 | E10: Creator fees and product costs excluded | F10: No | G10: =IF(F10="Yes",D10,0) -> 0
B11: SEO article pack: 2 researched articles | C11: Monthly | D11: 7000 | E11: Subject to medical/compliance review | F11: No | G11: =IF(F11="Yes",D11,0) -> 0
B12: Additional landing page | C12: Once-off | D12: 6500 | E12: Design, copy and build | F12: No | G12: =IF(F12="Yes",D12,0) -> 0
B13: Additional store products: 25 SKUs | C13: Once-off | D13: 5500 | E13: Client supplies approved data and imagery | F13: No | G13: =IF(F13="Yes",D13,0) -> 0
B14: Advanced CRM automation workflow | C14: Once-off | D14: 9500 | E14: One scoped automation journey | F14: No | G14: =IF(F14="Yes",D14,0) -> 0
B15: WhatsApp Business integration | C15: Once-off | D15: 12500 | E15: Provider fees and conversation charges excluded | F15: No | G15: =IF(F15="Yes",D15,0) -> 0
B16: Custom API/integration sprint | C16: Once-off | D16: 18000 | E16: Final price after technical discovery | F16: No | G16: =IF(F16="Yes",D16,0) -> 0
B17: Compliance/legal specialist review | C17: Once-off | D17: 15000 | E17: External specialist allowance; final quote may vary | F17: No | G17: =IF(F17="Yes",D17,0) -> 0
F18: Monthly add-ons total | G18: =SUMIFS(G6:G17,C6:C17,"Monthly") -> 0
F19: Once-off add-ons total | G19: =SUMIFS(G6:G17,C6:C17,"Once-off") -> 0

Sheet ROI Model
B2: ROI & BREAK-EVEN MODEL
B3: Illustrative commercial model. Replace yellow assumptions with NMS actuals before relying on outputs
B5: Business assumptions
B6: Average order / transaction value | C6: 950
B7: Gross margin after product/service delivery | C7: 0.55
B8: Website lead-to-sale conversion rate | C8: 0.1
B9: Average purchases per acquired customer in year 1 | C9: 1.4
B10: Current monthly website sessions | C10: 1500
B11: Current monthly qualified leads | C11: 80
B12: Current monthly new customers | C12: 8
B15: Selected package break-even
B16: Selected recurring monthly investment ex VAT | C16: ='Package Builder'!C19 -> 48375
B17: Gross profit per first transaction | C17: =C6*C7 -> 522.5
B18: Gross profit per acquired customer in year 1 | C18: =C6*C7*C9 -> 731.5
B19: New customers needed per month: first-order break-even | C19: =IFERROR(C16/C17,0) -> 92.583732
B20: New customers needed per month: year-1 gross-profit break-even | C20: =IFERROR(C16/C18,0) -> 66.131237
B21: Qualified leads needed at entered close rate | C21: =IFERROR(C20/C8,0) -> 661.31237
B22: Required increase over current new customers | C22: =IFERROR(C20/C12-1,0) -> 7.2664046
B25: Three planning scenarios
B26: Metric | C26: Conservative | D26: Base | E26: Upside
B27: Incremental qualified leads / month | C27: 60 | D27: 120 | E27: 220
B28: Lead-to-sale conversion | C28: 0.07 | D28: 0.1 | E28: 0.13
B29: New customers / month | C29: =C27*C28 -> 4.2 | D29: =D27*D28 -> 12 | E29: =E27*E28 -> 28.6
B30: Year-1 attributable revenue | C30: =C29*$C$6*$C$9*12 -> 67032 | D30: =D29*$C$6*$C$9*12 -> 191520 | E30: =E29*$C$6*$C$9*12 -> 456456
B31: Year-1 attributable gross profit | C31: =C30*$C$7 -> 36867.6 | D31: =D30*$C$7 -> 105336 | E31: =E30*$C$7 -> 251050.8
B32: 12-month programme investment ex VAT | C32: ='Package Builder'!C19*12+'Add-Ons'!G19 -> 580500 | D32: ='Package Builder'!C19*12+'Add-Ons'!G19 -> 580500 | E32: ='Package Builder'!C19*12+'Add-Ons'!G19 -> 580500
B33: Illustrative gross-profit ROI | C33: =IFERROR((C31-C32)/C32,0) -> -0.93648992 | D33: =IFERROR((D31-D32)/D32,0) -> -0.81854264 | E33: =IFERROR((E31-E32)/E32,0) -> -0.56752661
B36: Interpretation: “attributable” means sales reasonably linked to tracked marketing journeys, not all company sales. Gross-profit ROI = (attributable gross profit − programme investment) ÷ programme investment. It excludes tax, working capital, inventory constraints, refunds and sales-team costs. Replace assumptions with verified NMS figures and agree an attribution window. No agency can responsibly guarantee these outcomes; this model shows what must be true for the investment to pay back.
